var pt_central_vila_conde_monumentos_historicos =
{"type":"FeatureCollection","features":[{"type":"Feature","id":0,"geometry":{"type":"Point","coordinates":[-8.6435600000000008,41.267650000000003]},"properties":{"FID":0,"LINK_ID":717590256,"POI_ID":67179623,"SEQ_NUM":1,"FAC_TYPE":5999,"POI_NAME":"Igreja de S. Cosme e S. Damião","POI_LANGCD":"POR","POI_NMTYPE":"B","POI_ST_NUM":" ","ST_NUM_FUL":" ","ST_NFUL_LC":" ","ST_NAME":"Avenida Padre Teixeira das Neves","ST_LANGCD":"POR","POI_ST_SD":"R","ACC_TYPE":" ","PH_NUMBER":" ","CHAIN_ID":0,"NAT_IMPORT":"N","PRIVATE":"N","IN_VICIN":"N","NUM_PARENT":0,"NUM_CHILD":0,"PERCFRREF":90,"VANCITY_ID":0,"ACT_ADDR":" ","ACT_LANGCD":" ","ACT_ST_NAM":" ","ACT_ST_NUM":" ","ACT_ADMIN":" ","ACT_POSTAL":" ","OPEN_24":" ","DIESEL":" ","BLD_TYPE":" ","ENTR_TYPE":" ","FP_ID":0,"FP_TYPE":" ","LINK_SIDE":" ","POPULATION":0,"CAPITAL":" ","CLAIMED_BY":" ","CONTROL_BY":" ","FOOD_TYPE":" ","ALT_FOOD":" ","REG_FOOD":" ","RSTR_TYPE":" ","AIRPT_TYPE":" ","REST_TYPE":" "}}]}