var pt_central_vila_conde_museus =
{"type":"FeatureCollection","features":[{"type":"Feature","id":0,"geometry":{"type":"Point","coordinates":[-8.6747999999999994,41.326210000000003]},"properties":{"FID":0,"LINK_ID":587734498,"POI_ID":800061544,"SEQ_NUM":1,"FAC_TYPE":8410,"POI_NAME":"Museu Agrícola Entre Douro e Minho","POI_LANGCD":"POR","POI_NMTYPE":"B","POI_ST_NUM":" ","ST_NUM_FUL":" ","ST_NFUL_LC":" ","ST_NAME":"Rua da Agrária","ST_LANGCD":"POR","POI_ST_SD":"L","ACC_TYPE":" ","PH_NUMBER":"252660450","CHAIN_ID":0,"NAT_IMPORT":"N","PRIVATE":"N","IN_VICIN":"N","NUM_PARENT":0,"NUM_CHILD":0,"PERCFRREF":40,"VANCITY_ID":0,"ACT_ADDR":" ","ACT_LANGCD":" ","ACT_ST_NAM":" ","ACT_ST_NUM":" ","ACT_ADMIN":" ","ACT_POSTAL":" ","OPEN_24":" ","DIESEL":" ","BLD_TYPE":" ","ENTR_TYPE":" ","FP_ID":0,"FP_TYPE":" ","LINK_SIDE":" ","POPULATION":0,"CAPITAL":" ","CLAIMED_BY":" ","CONTROL_BY":" ","FOOD_TYPE":" ","ALT_FOOD":" ","REG_FOOD":" ","RSTR_TYPE":" ","AIRPT_TYPE":" ","REST_TYPE":" "}},{"type":"Feature","id":1,"geometry":{"type":"Point","coordinates":[-8.68093,41.284080000000003]},"properties":{"FID":1,"LINK_ID":587714624,"POI_ID":1122673137,"SEQ_NUM":1,"FAC_TYPE":8410,"POI_NAME":"Museu Vivo da Comutação Manual","POI_LANGCD":"POR","POI_NMTYPE":"B","POI_ST_NUM":" ","ST_NUM_FUL":" ","ST_NFUL_LC":" ","ST_NAME":"Rua Alberto Moreira","ST_LANGCD":"POR","POI_ST_SD":"L","ACC_TYPE":" ","PH_NUMBER":"229271643","CHAIN_ID":0,"NAT_IMPORT":"N","PRIVATE":"N","IN_VICIN":"N","NUM_PARENT":0,"NUM_CHILD":0,"PERCFRREF":70,"VANCITY_ID":0,"ACT_ADDR":" ","ACT_LANGCD":" ","ACT_ST_NAM":" ","ACT_ST_NUM":" ","ACT_ADMIN":" ","ACT_POSTAL":" ","OPEN_24":" ","DIESEL":" ","BLD_TYPE":" ","ENTR_TYPE":" ","FP_ID":0,"FP_TYPE":" ","LINK_SIDE":" ","POPULATION":0,"CAPITAL":" ","CLAIMED_BY":" ","CONTROL_BY":" ","FOOD_TYPE":" ","ALT_FOOD":" ","REG_FOOD":" ","RSTR_TYPE":" ","AIRPT_TYPE":" ","REST_TYPE":" "}}]}