var pt_central_valenca_restauracao =
{"type":"FeatureCollection","features":[{"type":"Feature","id":0,"geometry":{"type":"Point","coordinates":[-8.6413499999999992,42.027589999999996]},"properties":{"FID":0,"LINK_ID":590724062,"POI_ID":898978064,"SEQ_NUM":1,"FAC_TYPE":5800,"POI_NAME":"Coroa Verde","POI_LANGCD":"POR","POI_NMTYPE":"B","POI_ST_NUM":"15","ST_NUM_FUL":" ","ST_NFUL_LC":" ","ST_NAME":"Rua Trás do Jardim","ST_LANGCD":"POR","POI_ST_SD":"R","ACC_TYPE":" ","PH_NUMBER":"251825759","CHAIN_ID":0,"NAT_IMPORT":"N","PRIVATE":"N","IN_VICIN":"N","NUM_PARENT":0,"NUM_CHILD":0,"PERCFRREF":0,"VANCITY_ID":0,"ACT_ADDR":" ","ACT_LANGCD":" ","ACT_ST_NAM":" ","ACT_ST_NUM":" ","ACT_ADMIN":" ","ACT_POSTAL":" ","OPEN_24":" ","DIESEL":" ","BLD_TYPE":" ","ENTR_TYPE":" ","FP_ID":0,"FP_TYPE":" ","LINK_SIDE":" ","POPULATION":0,"CAPITAL":" ","CLAIMED_BY":" ","CONTROL_BY":" ","FOOD_TYPE":"Portuguese Food","ALT_FOOD":" ","REG_FOOD":" ","RSTR_TYPE":" ","AIRPT_TYPE":" ","REST_TYPE":" "}},{"type":"Feature","id":1,"geometry":{"type":"Point","coordinates":[-8.6449099999999994,42.02928]},"properties":{"FID":1,"LINK_ID":590722999,"POI_ID":67194814,"SEQ_NUM":1,"FAC_TYPE":5800,"POI_NAME":"Fortaleza de Valença","POI_LANGCD":"POR","POI_NMTYPE":"B","POI_ST_NUM":"5","ST_NUM_FUL":" ","ST_NFUL_LC":" ","ST_NAME":"Rua Apolinário da Fonseca","ST_LANGCD":"POR","POI_ST_SD":"L","ACC_TYPE":" ","PH_NUMBER":"251823146","CHAIN_ID":0,"NAT_IMPORT":"N","PRIVATE":"N","IN_VICIN":"N","NUM_PARENT":0,"NUM_CHILD":0,"PERCFRREF":0,"VANCITY_ID":0,"ACT_ADDR":" ","ACT_LANGCD":" ","ACT_ST_NAM":" ","ACT_ST_NUM":" ","ACT_ADMIN":" ","ACT_POSTAL":" ","OPEN_24":" ","DIESEL":" ","BLD_TYPE":" ","ENTR_TYPE":" ","FP_ID":0,"FP_TYPE":" ","LINK_SIDE":" ","POPULATION":0,"CAPITAL":" ","CLAIMED_BY":" ","CONTROL_BY":" ","FOOD_TYPE":"Portuguese Food","ALT_FOOD":" ","REG_FOOD":" ","RSTR_TYPE":" ","AIRPT_TYPE":" ","REST_TYPE":" "}}]}