var pt_costa_matosinhos_forcas_seguranca = 
{"type":"FeatureCollection","features":[{"type":"Feature","id":0,"geometry":{"type":"Point","coordinates":[-8.6439599999999999,41.199570000000001]},"properties":{"FID":0,"LINK_ID":575144185,"POI_ID":1200769565,"SEQ_NUM":1,"FAC_TYPE":9525,"POI_NAME":"Custóias-Matosinhos-Esquadra","POI_LANGCD":"POR","POI_NMTYPE":"B","POI_ST_NUM":" ","ST_NUM_FUL":" ","ST_NFUL_LC":" ","ST_NAME":"M1386","ST_LANGCD":"POR","POI_ST_SD":"L","ACC_TYPE":" ","PH_NUMBER":"229577940","CHAIN_ID":0,"NAT_IMPORT":"N","PRIVATE":"N","IN_VICIN":"N","NUM_PARENT":0,"NUM_CHILD":0,"PERCFRREF":61,"VANCITY_ID":0,"ACT_ADDR":" ","ACT_LANGCD":" ","ACT_ST_NAM":" ","ACT_ST_NUM":" ","ACT_ADMIN":" ","ACT_POSTAL":" ","OPEN_24":" ","DIESEL":" ","BLD_TYPE":" ","ENTR_TYPE":" ","FP_ID":0,"FP_TYPE":" ","LINK_SIDE":" ","POPULATION":0,"CAPITAL":" ","CLAIMED_BY":" ","CONTROL_BY":" ","FOOD_TYPE":" ","ALT_FOOD":" ","REG_FOOD":" ","RSTR_TYPE":" ","AIRPT_TYPE":" ","REST_TYPE":" "}},{"type":"Feature","id":1,"geometry":{"type":"Point","coordinates":[-8.6377699999999997,41.215539999999997]},"properties":{"FID":1,"LINK_ID":1134013503,"POI_ID":899001715,"SEQ_NUM":1,"FAC_TYPE":9221,"POI_NAME":"GNR de Leça do Balio","POI_LANGCD":"POR","POI_NMTYPE":"B","POI_ST_NUM":" ","ST_NUM_FUL":" ","ST_NFUL_LC":" ","ST_NAME":"Rua José Ribeiro","ST_LANGCD":"POR","POI_ST_SD":"L","ACC_TYPE":" ","PH_NUMBER":"229516398","CHAIN_ID":0,"NAT_IMPORT":"N","PRIVATE":"N","IN_VICIN":"N","NUM_PARENT":0,"NUM_CHILD":0,"PERCFRREF":48,"VANCITY_ID":0,"ACT_ADDR":" ","ACT_LANGCD":" ","ACT_ST_NAM":" ","ACT_ST_NUM":" ","ACT_ADMIN":" ","ACT_POSTAL":" ","OPEN_24":" ","DIESEL":" ","BLD_TYPE":" ","ENTR_TYPE":" ","FP_ID":0,"FP_TYPE":" ","LINK_SIDE":" ","POPULATION":0,"CAPITAL":" ","CLAIMED_BY":" ","CONTROL_BY":" ","FOOD_TYPE":" ","ALT_FOOD":" ","REG_FOOD":" ","RSTR_TYPE":" ","AIRPT_TYPE":" ","REST_TYPE":" "}},{"type":"Feature","id":2,"geometry":{"type":"Point","coordinates":[-8.6439400000000006,41.199509999999997]},"properties":{"FID":2,"LINK_ID":575144185,"POI_ID":899031790,"SEQ_NUM":1,"FAC_TYPE":9221,"POI_NAME":"GNR de Custóias","POI_LANGCD":"POR","POI_NMTYPE":"B","POI_ST_NUM":" ","ST_NUM_FUL":" ","ST_NFUL_LC":" ","ST_NAME":"Rua Nova de São Gens","ST_LANGCD":"POR","POI_ST_SD":"L","ACC_TYPE":" ","PH_NUMBER":"229577940","CHAIN_ID":0,"NAT_IMPORT":"N","PRIVATE":"N","IN_VICIN":"N","NUM_PARENT":0,"NUM_CHILD":0,"PERCFRREF":0,"VANCITY_ID":0,"ACT_ADDR":" ","ACT_LANGCD":" ","ACT_ST_NAM":" ","ACT_ST_NUM":" ","ACT_ADMIN":" ","ACT_POSTAL":" ","OPEN_24":" ","DIESEL":" ","BLD_TYPE":" ","ENTR_TYPE":" ","FP_ID":0,"FP_TYPE":" ","LINK_SIDE":" ","POPULATION":0,"CAPITAL":" ","CLAIMED_BY":" ","CONTROL_BY":" ","FOOD_TYPE":" ","ALT_FOOD":" ","REG_FOOD":" ","RSTR_TYPE":" ","AIRPT_TYPE":" ","REST_TYPE":" "}}]}