{"type":"FeatureCollection","features":[{"type":"Feature","id":0,"geometry":{"type":"Point","coordinates":[-8.6239600000000003,41.179519999999997]},"properties":{"FID":0,"LINK_ID":811552802,"POI_ID":998230247,"SEQ_NUM":1,"FAC_TYPE":7011,"POI_NAME":"Star Inn Porto","POI_LANGCD":"POR","POI_NMTYPE":"B","POI_ST_NUM":"930","ST_NUM_FUL":" ","ST_NFUL_LC":" ","ST_NAME":"Rua da Senhora do Porto","ST_LANGCD":"POR","POI_ST_SD":"L","ACC_TYPE":" ","PH_NUMBER":"228347000","CHAIN_ID":0,"NAT_IMPORT":"N","PRIVATE":"N","IN_VICIN":"N","NUM_PARENT":0,"NUM_CHILD":0,"PERCFRREF":0,"VANCITY_ID":0,"ACT_ADDR":" ","ACT_LANGCD":" ","ACT_ST_NAM":" ","ACT_ST_NUM":" ","ACT_ADMIN":" ","ACT_POSTAL":" ","OPEN_24":" ","DIESEL":" ","BLD_TYPE":" ","ENTR_TYPE":" ","FP_ID":0,"FP_TYPE":" ","LINK_SIDE":" ","POPULATION":0,"CAPITAL":" ","CLAIMED_BY":" ","CONTROL_BY":" ","FOOD_TYPE":" ","ALT_FOOD":" ","REG_FOOD":" ","RSTR_TYPE":" ","AIRPT_TYPE":" ","REST_TYPE":" "}},{"type":"Feature","id":1,"geometry":{"type":"Point","coordinates":[-8.6254000000000008,41.188890000000001]},"properties":{"FID":1,"LINK_ID":575145617,"POI_ID":1141483675,"SEQ_NUM":1,"FAC_TYPE":7011,"POI_NAME":"Portofino Hotel Motel","POI_LANGCD":"POR","POI_NMTYPE":"B","POI_ST_NUM":"972","ST_NUM_FUL":" ","ST_NFUL_LC":" ","ST_NAME":"Rua José Maria Baptista Valente","ST_LANGCD":"POR","POI_ST_SD":"R","ACC_TYPE":" ","PH_NUMBER":"229050120","CHAIN_ID":0,"NAT_IMPORT":"N","PRIVATE":"N","IN_VICIN":"N","NUM_PARENT":0,"NUM_CHILD":0,"PERCFRREF":4,"VANCITY_ID":0,"ACT_ADDR":" ","ACT_LANGCD":" ","ACT_ST_NAM":" ","ACT_ST_NUM":" ","ACT_ADMIN":" ","ACT_POSTAL":" ","OPEN_24":" ","DIESEL":" ","BLD_TYPE":" ","ENTR_TYPE":" ","FP_ID":0,"FP_TYPE":" ","LINK_SIDE":" ","POPULATION":0,"CAPITAL":" ","CLAIMED_BY":" ","CONTROL_BY":" ","FOOD_TYPE":" ","ALT_FOOD":" ","REG_FOOD":" ","RSTR_TYPE":" ","AIRPT_TYPE":" ","REST_TYPE":" "}}]}