var pt_costa_maia_estabelecimentos_comerciais =
{"type":"FeatureCollection","features":[{"type":"Feature","id":0,"geometry":{"type":"Point","coordinates":[-8.6657700000000002,41.249920000000003]},"properties":{"FID":0,"LINK_ID":717622149,"POI_ID":1141555876,"SEQ_NUM":1,"FAC_TYPE":5540,"POI_NAME":"INTERMARCHÉ","POI_LANGCD":"POR","POI_NMTYPE":"B","POI_ST_NUM":" ","ST_NUM_FUL":" ","ST_NFUL_LC":" ","ST_NAME":" ","ST_LANGCD":" ","POI_ST_SD":"L","ACC_TYPE":" ","PH_NUMBER":"229435740","CHAIN_ID":786,"NAT_IMPORT":"N","PRIVATE":"N","IN_VICIN":"N","NUM_PARENT":0,"NUM_CHILD":0,"PERCFRREF":81,"VANCITY_ID":0,"ACT_ADDR":" ","ACT_LANGCD":" ","ACT_ST_NAM":" ","ACT_ST_NUM":" ","ACT_ADMIN":" ","ACT_POSTAL":" ","OPEN_24":"N","DIESEL":" ","BLD_TYPE":" ","ENTR_TYPE":" ","FP_ID":0,"FP_TYPE":" ","LINK_SIDE":" ","POPULATION":0,"CAPITAL":" ","CLAIMED_BY":" ","CONTROL_BY":" ","FOOD_TYPE":" ","ALT_FOOD":" ","REG_FOOD":" ","RSTR_TYPE":" ","AIRPT_TYPE":" ","REST_TYPE":" "}},{"type":"Feature","id":1,"geometry":{"type":"Point","coordinates":[-8.6591900000000006,41.2502]},"properties":{"FID":1,"LINK_ID":576716880,"POI_ID":1104231648,"SEQ_NUM":1,"FAC_TYPE":5400,"POI_NAME":"Banquete","POI_LANGCD":"POR","POI_NMTYPE":"B","POI_ST_NUM":" ","ST_NUM_FUL":" ","ST_NFUL_LC":" ","ST_NAME":"Rua 4","ST_LANGCD":"POR","POI_ST_SD":"R","ACC_TYPE":" ","PH_NUMBER":"229422532","CHAIN_ID":0,"NAT_IMPORT":"N","PRIVATE":"N","IN_VICIN":"N","NUM_PARENT":0,"NUM_CHILD":0,"PERCFRREF":1,"VANCITY_ID":0,"ACT_ADDR":" ","ACT_LANGCD":" ","ACT_ST_NAM":" ","ACT_ST_NUM":" ","ACT_ADMIN":" ","ACT_POSTAL":" ","OPEN_24":" ","DIESEL":" ","BLD_TYPE":" ","ENTR_TYPE":" ","FP_ID":0,"FP_TYPE":" ","LINK_SIDE":" ","POPULATION":0,"CAPITAL":" ","CLAIMED_BY":" ","CONTROL_BY":" ","FOOD_TYPE":" ","ALT_FOOD":" ","REG_FOOD":" ","RSTR_TYPE":" ","AIRPT_TYPE":" ","REST_TYPE":" "}},{"type":"Feature","id":2,"geometry":{"type":"Point","coordinates":[-8.6629900000000006,41.247619999999998]},"properties":{"FID":2,"LINK_ID":576717084,"POI_ID":1031658044,"SEQ_NUM":1,"FAC_TYPE":5400,"POI_NAME":"Mercados Anazário","POI_LANGCD":"POR","POI_NMTYPE":"B","POI_ST_NUM":"1263","ST_NUM_FUL":" ","ST_NFUL_LC":" ","ST_NAME":"Rua do Doutor Farinhote","ST_LANGCD":"POR","POI_ST_SD":"R","ACC_TYPE":" ","PH_NUMBER":"229410985","CHAIN_ID":0,"NAT_IMPORT":"N","PRIVATE":"N","IN_VICIN":"N","NUM_PARENT":0,"NUM_CHILD":0,"PERCFRREF":0,"VANCITY_ID":0,"ACT_ADDR":" ","ACT_LANGCD":" ","ACT_ST_NAM":" ","ACT_ST_NUM":" ","ACT_ADMIN":" ","ACT_POSTAL":" ","OPEN_24":" ","DIESEL":" ","BLD_TYPE":" ","ENTR_TYPE":" ","FP_ID":0,"FP_TYPE":" ","LINK_SIDE":" ","POPULATION":0,"CAPITAL":" ","CLAIMED_BY":" ","CONTROL_BY":" ","FOOD_TYPE":" ","ALT_FOOD":" ","REG_FOOD":" ","RSTR_TYPE":" ","AIRPT_TYPE":" ","REST_TYPE":" "}},{"type":"Feature","id":3,"geometry":{"type":"Point","coordinates":[-8.6655599999999993,41.249650000000003]},"properties":{"FID":3,"LINK_ID":717622149,"POI_ID":1141555879,"SEQ_NUM":1,"FAC_TYPE":5400,"POI_NAME":"INTERMARCHÉ","POI_LANGCD":"POR","POI_NMTYPE":"B","POI_ST_NUM":" ","ST_NUM_FUL":" ","ST_NFUL_LC":" ","ST_NAME":" ","ST_LANGCD":" ","POI_ST_SD":"L","ACC_TYPE":" ","PH_NUMBER":" ","CHAIN_ID":786,"NAT_IMPORT":"N","PRIVATE":"N","IN_VICIN":"N","NUM_PARENT":0,"NUM_CHILD":0,"PERCFRREF":38,"VANCITY_ID":0,"ACT_ADDR":" ","ACT_LANGCD":" ","ACT_ST_NAM":" ","ACT_ST_NUM":" ","ACT_ADMIN":" ","ACT_POSTAL":" ","OPEN_24":" ","DIESEL":" ","BLD_TYPE":" ","ENTR_TYPE":" ","FP_ID":0,"FP_TYPE":" ","LINK_SIDE":" ","POPULATION":0,"CAPITAL":" ","CLAIMED_BY":" ","CONTROL_BY":" ","FOOD_TYPE":" ","ALT_FOOD":" ","REG_FOOD":" ","RSTR_TYPE":" ","AIRPT_TYPE":" ","REST_TYPE":" "}}]}