var pt_central_barcelos_forcas_seguranca =
{"type":"FeatureCollection","features":[{"type":"Feature","id":0,"geometry":{"type":"Point","coordinates":[-8.6216799999999996,41.524209999999997]},"properties":{"FID":0,"LINK_ID":591189566,"POI_ID":936007258,"SEQ_NUM":1,"FAC_TYPE":9221,"POI_NAME":"GNR de Barcelos","POI_LANGCD":"POR","POI_NMTYPE":"B","POI_ST_NUM":"17","ST_NUM_FUL":" ","ST_NFUL_LC":" ","ST_NAME":"Rua Brito Lima","ST_LANGCD":"POR","POI_ST_SD":"L","ACC_TYPE":" ","PH_NUMBER":"253832500","CHAIN_ID":0,"NAT_IMPORT":"N","PRIVATE":"N","IN_VICIN":"N","NUM_PARENT":0,"NUM_CHILD":0,"PERCFRREF":0,"VANCITY_ID":0,"ACT_ADDR":" ","ACT_LANGCD":" ","ACT_ST_NAM":" ","ACT_ST_NUM":" ","ACT_ADMIN":" ","ACT_POSTAL":" ","OPEN_24":" ","DIESEL":" ","BLD_TYPE":" ","ENTR_TYPE":" ","FP_ID":0,"FP_TYPE":" ","LINK_SIDE":" ","POPULATION":0,"CAPITAL":" ","CLAIMED_BY":" ","CONTROL_BY":" ","FOOD_TYPE":" ","ALT_FOOD":" ","REG_FOOD":" ","RSTR_TYPE":" ","AIRPT_TYPE":" ","REST_TYPE":" "}},{"type":"Feature","id":1,"geometry":{"type":"Point","coordinates":[-8.6176100000000009,41.531669999999998]},"properties":{"FID":1,"LINK_ID":591115927,"POI_ID":936007257,"SEQ_NUM":1,"FAC_TYPE":9221,"POI_NAME":"PSP de Barcelos","POI_LANGCD":"POR","POI_NMTYPE":"B","POI_ST_NUM":"537","ST_NUM_FUL":" ","ST_NFUL_LC":" ","ST_NAME":"Avenida Doutor Sidónio Pais","ST_LANGCD":"POR","POI_ST_SD":"R","ACC_TYPE":" ","PH_NUMBER":"253802570","CHAIN_ID":0,"NAT_IMPORT":"N","PRIVATE":"N","IN_VICIN":"N","NUM_PARENT":0,"NUM_CHILD":0,"PERCFRREF":0,"VANCITY_ID":0,"ACT_ADDR":" ","ACT_LANGCD":" ","ACT_ST_NAM":" ","ACT_ST_NUM":" ","ACT_ADMIN":" ","ACT_POSTAL":" ","OPEN_24":" ","DIESEL":" ","BLD_TYPE":" ","ENTR_TYPE":" ","FP_ID":0,"FP_TYPE":" ","LINK_SIDE":" ","POPULATION":0,"CAPITAL":" ","CLAIMED_BY":" ","CONTROL_BY":" ","FOOD_TYPE":" ","ALT_FOOD":" ","REG_FOOD":" ","RSTR_TYPE":" ","AIRPT_TYPE":" ","REST_TYPE":" "}},{"type":"Feature","id":2,"geometry":{"type":"Point","coordinates":[-8.61754,41.531669999999998]},"properties":{"FID":2,"LINK_ID":591115927,"POI_ID":1200770322,"SEQ_NUM":1,"FAC_TYPE":9525,"POI_NAME":"Barcelos-Esquadra","POI_LANGCD":"POR","POI_NMTYPE":"B","POI_ST_NUM":"537","ST_NUM_FUL":" ","ST_NFUL_LC":" ","ST_NAME":"Avenida Doutor Sidónio Pais","ST_LANGCD":"POR","POI_ST_SD":"R","ACC_TYPE":" ","PH_NUMBER":"253802570","CHAIN_ID":0,"NAT_IMPORT":"N","PRIVATE":"N","IN_VICIN":"N","NUM_PARENT":0,"NUM_CHILD":0,"PERCFRREF":36,"VANCITY_ID":0,"ACT_ADDR":" ","ACT_LANGCD":" ","ACT_ST_NAM":" ","ACT_ST_NUM":" ","ACT_ADMIN":" ","ACT_POSTAL":" ","OPEN_24":" ","DIESEL":" ","BLD_TYPE":" ","ENTR_TYPE":" ","FP_ID":0,"FP_TYPE":" ","LINK_SIDE":" ","POPULATION":0,"CAPITAL":" ","CLAIMED_BY":" ","CONTROL_BY":" ","FOOD_TYPE":" ","ALT_FOOD":" ","REG_FOOD":" ","RSTR_TYPE":" ","AIRPT_TYPE":" ","REST_TYPE":" "}}]}