var pt_central_paredes_coura_farmacias =
{"type":"FeatureCollection","features":[{"type":"Feature","id":0,"geometry":{"type":"Point","coordinates":[-8.6261500000000009,41.888770000000001]},"properties":{"FID":0,"LINK_ID":590773974,"POI_ID":898993446,"SEQ_NUM":1,"FAC_TYPE":9565,"POI_NAME":"Farmácia Sousa","POI_LANGCD":"POR","POI_NMTYPE":"B","POI_ST_NUM":" ","ST_NUM_FUL":" ","ST_NFUL_LC":" ","ST_NAME":"N201","ST_LANGCD":"POR","POI_ST_SD":"L","ACC_TYPE":" ","PH_NUMBER":"251943358","CHAIN_ID":0,"NAT_IMPORT":"N","PRIVATE":"N","IN_VICIN":"N","NUM_PARENT":0,"NUM_CHILD":0,"PERCFRREF":30,"VANCITY_ID":0,"ACT_ADDR":" ","ACT_LANGCD":" ","ACT_ST_NAM":" ","ACT_ST_NUM":" ","ACT_ADMIN":" ","ACT_POSTAL":" ","OPEN_24":" ","DIESEL":" ","BLD_TYPE":" ","ENTR_TYPE":" ","FP_ID":0,"FP_TYPE":" ","LINK_SIDE":" ","POPULATION":0,"CAPITAL":" ","CLAIMED_BY":" ","CONTROL_BY":" ","FOOD_TYPE":" ","ALT_FOOD":" ","REG_FOOD":" ","RSTR_TYPE":" ","AIRPT_TYPE":" ","REST_TYPE":" "}}]}